{
    "DND5E.title": "DnD5e Game System",
    "DND5E.AbbreviationCR": "VD",
    "DND5E.AbbreviationConc": "Conc.",
    "DND5E.AbbreviationDC": "CD",
    "DND5E.AbbreviationLR": "LR",
    "DND5E.AbbreviationLevel": "Nvl.",
    "DND5E.AbbreviationLbs": "lbs.",
    "DND5E.AbbreviationSR": "SR",
    "DND5E.Ability": "Característica",
    "DND5E.AbilityStr": "Fuerza",
    "DND5E.AbilityStrAbbr": "fue",
    "DND5E.AbilityCon": "Constitución",
    "DND5E.AbilityConAbbr": "con",
    "DND5E.AbilityDex": "Destreza",
    "DND5E.AbilityDexAbbr": "des",
    "DND5E.AbilityInt": "Inteligencia",
    "DND5E.AbilityIntAbbr": "int",
    "DND5E.AbilityWis": "Sabiduría",
    "DND5E.AbilityWisAbbr": "sab",
    "DND5E.AbilityCha": "Carisma",
    "DND5E.AbilityChaAbbr": "car",
    "DND5E.AbilityModifier": "Modificador de Característica",
    "DND5E.AbilityPromptText": "¿Qué tipo de prueba de {ability}?",
    "DND5E.AbilityPromptTitle": "Prueba de Característica de {ability}",
    "DND5E.AbilityUseHint": "Determina cómo utilizar el {type} {name}.",
    "DND5E.AbilityUseUnavailableHint": "¡No quedan usos para este elemento!",
    "DND5E.AbilityUseChargedHint": "¡Este {type} está cargado y listo para usar!",
    "DND5E.AbilityUseRechargedHint": "¡Este {type} está agotado y debe recargarse!",
    "DND5E.AbilityUseNormalHint": "Este {type} tiene {value} de {max} usos por {per} restante.",
    "DND5E.AbilityUseConsumableChargeHint": "Usar este {type} consumirá 1 carga de {value} restante.",
    "DND5E.AbilityUseConsumableQuantityHint": "Usar este {type} consumirá 1 cantidad de {quantity} restante.",
    "DND5E.AbilityUseConsumableDestroyHint": "Usar este {type} consumirá su última carga y se destruirá.",
    "DND5E.AbilityUseConsume": "¿Consumir carga disponible?",
    "DND5E.AbilityUseChargesLabel": "{value} cargas",
    "DND5E.AbilityUseConsumableLabel": "{max} por {per}",
    "DND5E.AbilityUseCast": "Lanzar Conjuro",
    "DND5E.AbilityUseUse": "Utilizar Característica",
    
    "DND5E.Action": "Acción",
    "DND5E.ActionPl": "Acciones",
    "DND5E.ActionAbil": "Prueba de Característica",
    "DND5E.ActionHeal": "Curación",
    "DND5E.ActionMSAK": "Ataque con Conjuro Cuerpo a Cuerpo",
    "DND5E.ActionMWAK": "Ataque con Arma Cuerpo a Cuerpo",
    "DND5E.ActionOther": "Otro",
    "DND5E.ActionRSAK": "Ataque con Conjuro a Distancia",
    "DND5E.ActionRWAK": "Ataque con Arma a Distancia",
    "DND5E.ActionSave": "Tirada de salvación",
    "DND5E.ActionUtil": "Utilidad",
    "DND5E.ActionWarningNoItem": "El objeto seleccionado {item} ya no existe en el Personaje {name}.",
    "DND5E.ActionWarningNoToken": "Debes controlar uno o más tokens para poder utilizar esta opción.",
    "DND5E.Add": "Añadir",
    "DND5E.Advantage": "Ventaja",
    "DND5E.Alignment": "Alineamiento",
    "DND5E.AlignmentCE": "Caótico Malvado",
    "DND5E.AlignmentCG": "Caótico Bueno",
    "DND5E.AlignmentCN": "Caótico Neutral",
    "DND5E.AlignmentLE": "Legal Malvado",
    "DND5E.AlignmentLG": "Legal Bueno",
    "DND5E.AlignmentLN": "Legal Neutral",
    "DND5E.AlignmentNE": "Neutral Malvado",
    "DND5E.AlignmentNG": "Neutral Bueno",
    "DND5E.AlignmentTN": "Neutral",
    "DND5E.ArmorClass": "Clase de Armadura",
    "DND5E.AC": "CA",
    "DND5E.Attack": "Ataque",
    "DND5E.AttackPl": "Ataques",
    "DND5E.AttackRoll": "Tirada de Ataque",
    "DND5E.Attributes": "Atributos",
    "DND5E.Attuned": "En Sintonía",
    "DND5E.Background": "Trasfondo",
    "DND5E.Biography": "Biografía",
    "DND5E.BonusAbilityCheck": "Bonificación Global a las Pruebas de Característica",
    "DND5E.BonusAbilitySave": "Bonificación Global a las Tiradas de Salvación",
    "DND5E.BonusAbilitySkill": "Bonificación Global a las Pruebas de Habilidad",
    "DND5E.BonusAction": "Acción Adicional",
    "DND5E.BonusMSAttack": "Bonificación al Ataque con Conjuro Cuerpo a Cuerpo",
    "DND5E.BonusMSDamage": "Bonificación al Daño con Conjuro Cuerpo a Cuerpo",
    "DND5E.BonusMWAttack": "Bonificación al Ataque con Arma Cuerpo a Cuerpo",
    "DND5E.BonusMWDamage": "Bonificación al Daño con Arma Cuerpo a Cuerpo",
    "DND5E.BonusRSAttack": "Bonificación al Ataque con Conjuro a Distancia",
    "DND5E.BonusRSDamage": "Bonificación al Daño con Conjuro a Distancia",
    "DND5E.BonusRWAttack": "Bonificación al Ataque con Arma a Distancia",
    "DND5E.BonusRWDamage": "Bonificación al Daño con Arma a Distancia",
    "DND5E.BonusSaveForm": "Actualizar Bonificación",
    "DND5E.BonusSpellDC": "Bonificación Global a la CD de Conjuros",
    "DND5E.BonusTitle": "Configurar Bonificación de Personaje",
    "DND5E.Bonuses": "Bonificaciones Globales",
    "DND5E.BonusesHint": "Defina las bonificaciones globales como fórmulas que se agregarán a ciertas tiradas. Por ejemplo: 1d4 + 2",
    "DND5E.BonusesInstructions": "Configure las bonificaciones que se agregará al dado respectivo",
    "DND5E.ChallengeRating": "Valor de Dificultad",
    "DND5E.Charged": "Cargado",
    "DND5E.Charges": "Cargas",
    "DND5E.ChatContextDamage": "Aplicar Daño",
    "DND5E.ChatContextHealing": "Aplicar Curación",
    "DND5E.ChatContextDoubleDamage": "Aplicar Doble Daño",
    "DND5E.ChatContextHalfDamage": "Aplicar Mitad de Daño",
    "DND5E.ChatFlavor": "Mensaje Adicional en el Chat",
    "DND5E.ClassLevels": "Niveles de la Clase",
    "DND5E.ClassName": "Nombre de la Clase",
    "DND5E.ClassSkillsNumber": "N° de Habilidades Iniciales",
    "DND5E.ClassSkillsChosen": "Habilidades de Clase Elegidas",
    "DND5E.ComponentMaterial": "Material",
    "DND5E.ComponentSomatic": "Somático",
    "DND5E.ComponentVerbal": "Verbal",
    "DND5E.ConBlinded": "Cegado",
    "DND5E.ConCharmed": "Hechizado",
    "DND5E.ConDeafened": "Ensordecido",
    "DND5E.ConDiseased": "Enfermo",
    "DND5E.ConExhaustion": "Cansancio",
    "DND5E.ConFrightened": "Asustado",
    "DND5E.ConGrappled": "Agarrado",
    "DND5E.ConImm": "Inmunidad a Estados",
    "DND5E.ConIncapacitated": "Incapacitado",
    "DND5E.ConInvisible": "Invisible",
    "DND5E.ConParalyzed": "Paralizado",
    "DND5E.ConPetrified": "Petrificado",
    "DND5E.ConPoisoned": "Envenenado",
    "DND5E.ConProne": "Derribado",
    "DND5E.ConRestrained": "Apresado",
    "DND5E.ConStunned": "Aturdido",
    "DND5E.ConUnconscious": "Inconsciente",
    "DND5E.Concentration": "Concentración",

    "DND5E.ConsumeTitle": "Consumo de Recurso",
    "DND5E.ConsumeAmmunition": "Munición",
    "DND5E.ConsumeAttribute": "Atributo",
    "DND5E.ConsumeMaterial": "Material",
    "DND5E.ConsumeCharges": "Usos del Objeto",
    "DND5E.ConsumeWarningNoResource": "¡{name} está establecido a consumir {type} pero no se ha especificado ningún recurso!",
    "DND5E.ConsumeWarningNoSource": "¡La fuente {type} establecida que {name} consume ya no existe!",
    "DND5E.ConsumeWarningNoQuantity": "¡{name} se ha quedado sin su {type} establecido!",
    "DND5E.ConsumeWarningZeroAttribute": "¡{name} se ha quedado sin nada del recurso establecido!",

    "DND5E.ConsumableAmmunition": "Munición",
    "DND5E.ConsumableFood": "Comida",
    "DND5E.ConsumablePoison": "Veneno",
    "DND5E.ConsumablePotion": "Poción",
    "DND5E.ConsumableRod": "Vara",
    "DND5E.ConsumableScroll": "Pergamino",
    "DND5E.ConsumableTrinket": "Bagatela",
    "DND5E.ConsumableWand": "Varita",
    "DND5E.ConsumableUseWarnStart": "Este consumible tiene",
    "DND5E.ConsumableUseWarnEnd": "de la unidad actual",
    "DND5E.ConsumableUnitWarn": "unidades restantes",
    "DND5E.ConsumableLastChargeWarn": "Esta es la última carga de esta unidad y su consumo también reducirá la cantidad del elemento en 1",
    "DND5E.ConsumableWithoutCharges": "unidades disponibles para usar",
    "DND5E.Consumed": "Consumido",
    "DND5E.Cover": "Cobertura",
    "DND5E.CoverHalf": "Media",
    "DND5E.CoverThreeQuarters": "Tres cuartos",
    "DND5E.CoverTotal": "Completa",
    "DND5E.CostGP": "Coste (PO)",
    "DND5E.Critical": "Crítico",
    "DND5E.CriticalHit": "Golpe Crítico",
    "DND5E.Currency": "Monedas",
    "DND5E.CurrencyCP": "Cobre",
    "DND5E.CurrencyConvert": "Convertir todas las Monedas",
    "DND5E.CurrencyConvertHint": "Convierte todas las monedas del personaje a su máxima posible denominación para reducir la cantidad de monedas que lleva. Advertencia, esta acción no puede ser revertida.",
    "DND5E.CurrencyEP": "Electro",
    "DND5E.CurrencyGP": "Oro",
    "DND5E.CurrencyPP": "Platino",
    "DND5E.CurrencySP": "Plata",
    "DND5E.DamImm": "Inmunidad a Daño",
    "DND5E.DamRes": "Resistencia a Daño",
    "DND5E.DamVuln": "Vulnerabilidad a Daño",
    "DND5E.Damage": "Daño",
    "DND5E.DamageAcid": "Ácido",
    "DND5E.DamageBludgeoning": "Contundente",
    "DND5E.DamageCold": "Frío",
    "DND5E.DamageFire": "Fuego",
    "DND5E.DamageForce": "Fuerza",
    "DND5E.DamageLightning": "Relámpago",
    "DND5E.DamageNecrotic": "Necrótico",
    "DND5E.DamagePiercing": "Perforante",
    "DND5E.DamagePhysical": "Físico no-mágico",
    "DND5E.DamagePoison": "Veneno",
    "DND5E.DamagePsychic": "Psíquico",
    "DND5E.DamageRadiant": "Radiante",
    "DND5E.DamageRoll": "Tirada de Daño",
    "DND5E.DamageSlashing": "Cortante",
    "DND5E.DamageThunder": "Trueno",
    "DND5E.Day": "Día",
    "DND5E.DeathSave": "T.S. Contra Muerte",
    "DND5E.DeathSaveCriticalSuccess": "¡{name} consiguió un crítico en un tirada de salvación contra muerte y ha recuperado 1 punto de golpe!",
    "DND5E.DeathSaveSuccess": "¡{name} ha sobrevivido con 3 tiradas de salvación contra muerte exitosas.",
    "DND5E.DeathSaveFailure": "{name} ha muerto con 3 tiradas de salvación contra muerte fallidas!",
    "DND5E.DeathSavingThrow": "Tirada de Salvación contra Muerte",
    "DND5E.DeathSaveUnnecessary": "No necesitas tirar salvación de muerte porque tienes un número positivo de puntos de golpe o ya has alcanzado 3 éxitos o fallos.",
    "DND5E.Default": "Por Defecto",
    "DND5E.DefaultAbilityCheck": "Prueba de Característica por Defecto",
    "DND5E.Description": "Descripción",
    "DND5E.Details": "Detalles",
    "DND5E.Dimensions": "Dimensiones",
    "DND5E.Disadvantage": "Desventaja",
    "DND5E.DistAny": "Cualquiera",
    "DND5E.DistFt": "Pies",
    "DND5E.DistMi": "Millas",
    "DND5E.DistSelf": "Lanzador",
    "DND5E.DistTouch": "Toque",
    "DND5E.Duration": "Duración",
    "DND5E.EquipmentBonus": "Bonificación Mágica",
    "DND5E.EquipmentClothing": "Ropa",
    "DND5E.EquipmentHeavy": "Armadura Pesada",
    "DND5E.EquipmentLight": "Armadura Ligera",
    "DND5E.EquipmentMedium": "Armadura Media",
    "DND5E.EquipmentNatural": "Armadura Natural",
    "DND5E.EquipmentShield": "Escudo",
    "DND5E.EquipmentShieldProficiency": "Escudos",
    "DND5E.EquipmentTrinket": "Bagatela",
    "DND5E.EquipmentVehicle": "Equipo de vehículos",
    "DND5E.Equipped": "Equipado",
    "DND5E.Exhaustion": "Cansancio",
    "DND5E.Expertise": "Pericia",
    "DND5E.FeatureActionRecharge": "Recarga de Acción",

    "DND5E.ItemTypeClass": "Clase",
    "DND5E.ItemTypeClassPl": "Niveles de Clase",
    "DND5E.ItemTypeConsumable": "Consumible",
    "DND5E.ItemTypeConsumablePl": "Consumibles",
    "DND5E.ItemTypeContainer": "Contenedor",
    "DND5E.ItemTypeContainerPl": "Contenedores",
    "DND5E.ItemTypeEquipment": "Equipo",
    "DND5E.ItemTypeEquipmentPl": "Equipo",
    "DND5E.ItemTypeLoot": "Botín",
    "DND5E.ItemTypeLootPl": "Botín",
    "DND5E.ItemTypeTool": "Herramienta",
    "DND5E.ItemTypeToolPl": "Herramientas",
    "DND5E.ItemTypeSpell": "Conjuro",
    "DND5E.ItemTypeSpellPl": "Conjuros",
    "DND5E.ItemTypeWeapon": "Arma",
    "DND5E.ItemTypeWeaponPl": "Armas",
    "DND5E.ItemNoUses": "{name} no tiene usos disponibles restantes.",

    "DND5E.FeatureActive": "Capacidades Activas",
    "DND5E.FeatureAdd": "Crear Rasgo",
    "DND5E.FeatureAttack": "Ataque del Rasgo",
    "DND5E.FeaturePassive": "Capacidades Pasivas",
    "DND5E.FeatureRechargeOn": "Se recarga en",
    "DND5E.FeatureRechargeResult": "Resultado 1d6",
    "DND5E.FeatureUsage": "Uso del Rasgo",
    "DND5E.Features": "Rasgos",
    "DND5E.FeetAbbr": "pie.",
    "DND5E.Filter": "Filtro",
    "DND5E.FilterNoSpells": "No se encontraron conjuros con estos filtros.",
    "DND5E.NoSpellLevels": "Este personaje no tiene niveles de lanzador, pero puedes agregar conjuros manualmente.",

    "DND5E.FlagsInstructions": "Determine los rasgos y atributos del personaje para cambiar el comportamiento del sistema D&D5e",
    "DND5E.FlagsSave": "Actualizar Rasgos Especiales",
    "DND5E.FlagsTitle": "Configurar Rasgos Especiales",
    "DND5E.FlagsPowerfulBuild": "Forma Poderosa",
    "DND5E.FlagsPowerfulBuildHint": "Proporciona una capacidad de carga superior.",
    "DND5E.FlagsSavageAttacks": "Ataques Salvajes",
    "DND5E.FlagsSavageAttacksHint": "Añade un dado de daño extra en los críticos.",
    "DND5E.FlagsElvenAccuracy": "Precisión Élfica",
    "DND5E.FlagsElvenAccuracyHint": "Tira un d20 extra con ventaja para Des, Int, Sab, o Car.",
    "DND5E.FlagsHalflingLucky": "Suerte de Mediano",
    "DND5E.FlagsHalflingLuckyHint": "Vuelve a tirar pruebas de d20 cuando salga 1.",
    "DND5E.FlagsInitiativeAdv": "Ventaja en Iniciativa",
    "DND5E.FlagsInitiativeAdvHint": "De rasgos del personaje u objetos mágicos.",
    "DND5E.FlagsAlert": "Dote Alerta",
    "DND5E.FlagsAlertHint": "Provee +5 a la Iniciativa.",
    "DND5E.FlagsJOAT": "Aprendiz de Mucho",
    "DND5E.FlagsJOATHint": "Mitad de Competencia a las pruebas de habilidad en las que no eres Competente.",
    "DND5E.FlagsObservant": "Dote Observador",
    "DND5E.FlagsObservantHint": "Adquieres un modificador de +5 a tu Percepción e Investigación pasivas.",
    "DND5E.FlagsReliableTalent": "Talentos Fiables",
    "DND5E.FlagsReliableTalentHint": "Rasgo 'Talentos Fiables' del pícaro.",
    "DND5E.FlagsRemarkableAthlete": "Atleta Sobresaliente",
    "DND5E.FlagsRemarkableAthleteHint": "Mitad de Competencia (redondeado hacia arriba) a las pruebas de habilidad físicas y a la Iniciativa.",
    "DND5E.FlagsCritThreshold": "Umbral de Golpe Crítico",
    "DND5E.FlagsCritThresholdHint": "Permite una mayor probabilidad de golpe crítico; por ejemplo, Crítico Mejorado o Crítico Superior.",

    "DND5E.Flat": "Fijo",
    "DND5E.Formula": "Fórmula",
    "DND5E.GrantedAbilities": "Habilidades Otorgadas",
    "DND5E.HalfProficient": "Medio competente",
    "DND5E.Healing": "Curación",
    "DND5E.HealingTemp": "Curación (Temporal)",
    "DND5E.HitPoints": "Puntos de Golpe",
    "DND5E.HP": "PG",
    "DND5E.HealthConditions": "Estados de Salud",
    "DND5E.HPFormula": "Fórmula para Salud",
    "DND5E.HitDice": "Dados de Golpe",
    "DND5E.HitDiceRoll": "Tirar Dado de Golpe",
    "DND5E.HitDiceUsed": "Dados de Golpe Usados",
    "DND5E.HitDiceWarn": "¡{name} no tiene ningún dado de golpe {formula} restante!",
    "DND5E.Identified": "Identificado",
    "DND5E.Initiative": "Iniciativa",
    "DND5E.Inspiration": "Inspiración",
    "DND5E.Inventory": "Inventario",
    "DND5E.ItemActionType": "Tipo de Acción",
    "DND5E.ItemActivationCondition": "Condición para Activación",
    "DND5E.ItemActivationCost": "Coste de Activación",
    "DND5E.ItemAttackBonus": "Bono en Tirada de Ataque",
    "DND5E.ItemConsumableActivation": "Activación del Consumible",
    "DND5E.ItemConsumableUsage": "Uso del Consumible",
    "DND5E.ItemConsumableDetails": "Detalles del Consumible",
    "DND5E.ItemConsumableStatus": "Estado del Consumible",
    "DND5E.ItemConsumableType": "Tipo de Consumible",
    "DND5E.ItemContainerCapacity": "Capacidad",
    "DND5E.ItemContainerCapacityItems": "Objetos",
    "DND5E.ItemContainerCapacityType": "Tipo de Capacidad",
    "DND5E.ItemContainerCapacityWeight": "Peso",
    "DND5E.ItemContainerDetails": "Detalle del Contenedor",

    "DND5E.ItemContainerProperties": "Propiedades del Contenedor",
    "DND5E.ItemContainerWeightless": "Contenido sin peso",
    "DND5E.ItemCreate": "Crear Elemento",
    "DND5E.ItemDelete": "Eliminar Elemento",
    "DND5E.ItemDestroyEmpty": "Destruir al vaciar",
    "DND5E.ItemEdit": "Editar Elemento",
    "DND5E.ItemEquipmentAction": "Acción del Equipo",
    "DND5E.ItemEquipmentDetails": "Detalles del Equipo",
    "DND5E.ItemEquipmentDexMod": "Mod. de Destreza Máximo",

    "DND5E.ItemEquipmentStatus": "Estado del Equipo",
    "DND5E.ItemEquipmentStealthDisav": "Impone Desventaja en Sigilo",
    "DND5E.ItemEquipmentType": "Tipo de Equipo",
    "DND5E.ItemEquipmentUsage": "Uso del Equipo",

    "DND5E.ItemName": "Nombre del Elemento",
    "DND5E.ItemNew": "Nuevo {type}",
    "DND5E.ItemRechargeCheck": "¡{name} en la prueba de recarga",
    "DND5E.ItemRechargeFailure": "falla!",
    "DND5E.ItemRechargeSuccess": "tiene éxito!",
    "DND5E.ItemRequiredStr": "Fuerza Necesaria",
    "DND5E.ItemToolProficiency": "Competencia con Herramienta",

    "DND5E.ItemWeaponAttack": "Ataque del Arma",
    "DND5E.ItemWeaponDetails": "Detalles del Arma",
    "DND5E.ItemWeaponProperties": "Propiedades del Arma",

    "DND5E.ItemWeaponStatus": "Estado del Arma",
    "DND5E.ItemWeaponType": "Tipo de Arma",
    "DND5E.ItemWeaponUsage": "Uso del Arma",
    "DND5E.JackOfAllTrades": "Aprendiz de Mucho",
    "DND5E.LairAct": "Utiliza Acciones en Guarida",
    "DND5E.LairActionLabel": "Acciones en Guarida",
    "DND5E.Languages": "Idiomas",
    "DND5E.LanguagesAarakocra": "Aarakocra",
    "DND5E.LanguagesAbyssal": "Abisal",
    "DND5E.LanguagesAquan": "Acuano",
    "DND5E.LanguagesAuran": "Aurano",
    "DND5E.LanguagesCelestial": "Celestial",
    "DND5E.LanguagesCommon": "Común",
    "DND5E.LanguagesDeepSpeech": "Habla de las Profundidades",
    "DND5E.LanguagesDraconic": "Dracónico",
    "DND5E.LanguagesDruidic": "Druidico",
    "DND5E.LanguagesDwarvish": "Enano",
    "DND5E.LanguagesElvish": "Elfo",
    "DND5E.LanguagesGiant": "Gigante",
    "DND5E.LanguagesGith": "Gith",
    "DND5E.LanguagesGnoll": "Gnoll",
    "DND5E.LanguagesGnomish": "Gnomo",
    "DND5E.LanguagesGoblin": "Goblin",
    "DND5E.LanguagesHalfling": "Mediano",
    "DND5E.LanguagesIgnan": "Ígneo",
    "DND5E.LanguagesInfernal": "Infernal",
    "DND5E.LanguagesOrc": "Orco",
    "DND5E.LanguagesPrimordial": "Primordial",
    "DND5E.LanguagesSylvan": "Silvano",
    "DND5E.LanguagesTerran": "Terrano",
    "DND5E.LanguagesThievesCant": "Jerga de Ladrones",
    "DND5E.LanguagesUndercommon": "Infracomún",
    "DND5E.LegAct": "Acciones Legendarias",
    "DND5E.LegendaryActionLabel": "Acción Legendaria",
    "DND5E.LegRes": "Resistencia Legendaria",
    "DND5E.Level": "Nivel",
    "DND5E.LevelScaling": "Escala de Nivel",
    "DND5E.LimitedUses": "Usos Limitados",
    "DND5E.LongRest": "Descanso Largo",
    "DND5E.LongRestNormal": "Descanso Largo (8 horas)",
    "DND5E.LongRestGritty": "Descanso Largo (7 días)",
    "DND5E.LongRestEpic": "Descanso Largo (1 hora)",
    "DND5E.LongRestOvernight": "Descanso Largo (Nuevo Día)",
    "DND5E.LongRestResult": "{name} toma un descanso largo y recupera {health} puntos de golpe y {dice} dado(s) de golpe.",
    "DND5E.Max": "Máx",
    "DND5E.Modifier": "Modificador",
    "DND5E.Name": "Nombre del Personaje",
    "DND5E.NoCharges": "Sin Cargas",
    "DND5E.None": "Ninguno",
    "DND5E.Normal": "Normal",
    "DND5E.NotProficient": "No Competente",
    "DND5E.OtherFormula": "Otra Fórmula",
    "DND5E.PactMagic": "Magia del Pacto",
    "DND5E.Passive": "Pasivo",
    "DND5E.PlaceTemplate": "Colocar Plantilla de Medición",
    "DND5E.Polymorph": "Polimorfar",
    "DND5E.PolymorphAcceptSettings": "Ajustes Personalizados",
    "DND5E.PolymorphKeepBio": "Mantener biografía",
    "DND5E.PolymorphKeepClass": "Mantener bonifiación por competencia (deja ítems de clase en la hoja)",
    "DND5E.PolymorphKeepFeats": "Mantener rasgos",
    "DND5E.PolymorphKeepItems": "Mantener Equipo",
    "DND5E.PolymorphKeepMental": "Mantener puntuaciones de característica mentales (Int, Sab, Car)",
    "DND5E.PolymorphKeepPhysical": "Mantener puntuaciones de característica físicas (Fue, Des, Con)",
    "DND5E.PolymorphKeepSaves": "Mantener competencias de tiradas de salvación",
    "DND5E.PolymorphKeepSkills": "Mantener competencias de habilidades",
    "DND5E.PolymorphKeepSpells": "Mantener conjuros",
    "DND5E.PolymorphKeepVision": "Mantener visión (personaje y token)",
    "DND5E.PolymorphMergeSaves": "Mezclar competencias de tiradas de salvación (usar más alta)",
    "DND5E.PolymorphMergeSkills": "Mantener competencias de habilidades (usar más alta)",
    "DND5E.PolymorphPromptTitle": "Transformar Personaje",
    "DND5E.PolymorphRestoreTransformation": "Restaurar Transformación",
    "DND5E.PolymorphRevertWarn": "No tienes permiso para revertir el estado de polimorfismo de este personaje.",
    "DND5E.PolymorphTmpClass": "Clase Temporal",
    "DND5E.PolymorphTokens": "¿Transformar todos los tokens vinculados?",
    "DND5E.PolymorphWarn": "¡No tienes permiso para polimorfar a este personaje!",
    "DND5E.PolymorphWildShape": "Forma Salvaje",
    "DND5E.Prepared": "Preparado",
    "DND5E.Price": "Precio",
    "DND5E.Proficiency": "Competencia",
    "DND5E.Proficient": "Competente",
    "DND5E.Quantity": "Cantidad",
    "DND5E.Race": "Raza",
    "DND5E.Range": "Alcance",
    "DND5E.Rarity": "Rareza",
    "DND5E.Reaction": "Reacción",
    "DND5E.ReactionPl": "Reacciones",
    "DND5E.Recharge": "Recarga",
    "DND5E.RequiredMaterials": "Materiales Requeridos",
    "DND5E.Requirements": "Requisitos",
    "DND5E.ResourcePrimary": "Recurso 1",
    "DND5E.ResourceSecondary": "Recurso 2",
    "DND5E.ResourceTertiary": "Recurso 3",
    "DND5E.RestL": "Des. L.",
    "DND5E.RestS": "Des. C.",
    "DND5E.Ritual": "Ritual",
    "DND5E.Roll": "Tirada",
    "DND5E.RollExample": "p.ej. +1d4",
    "DND5E.RollMode": "Modo de Tirada",
    "DND5E.RollSituationalBonus": "¿Bono Situacional?",
    "DND5E.SavingThrow": "Tirada de Salvación",
    "DND5E.SavePromptTitle": "Tirada de salvación de {ability}",
    "DND5E.ScalingFormula": "Fórmula de Escala",
    "DND5E.SchoolAbj": "Abjuración",
    "DND5E.SchoolCon": "Conjuración",
    "DND5E.SchoolDiv": "Adivinación",
    "DND5E.SchoolEnc": "Encantamiento",
    "DND5E.SchoolEvo": "Evocación",
    "DND5E.SchoolIll": "Ilusionismo",
    "DND5E.SchoolNec": "Nigromancia",
    "DND5E.SchoolTrs": "Transmutación",
    "DND5E.SenseBS": "Visión Ciega",
    "DND5E.SenseDV": "Visión en la Oscuridad",
    "DND5E.SenseTR": "Visión Verdadera",
    "DND5E.SenseTS": "Sentir Vibraciones",
    "DND5E.Senses": "Sentidos",
    "DND5E.ShortRest": "Descanso Corto",
    "DND5E.ShortRestNormal": "Descanso Corto (1 hora)",
    "DND5E.ShortRestGritty": "Descanso Corto (8 horas)",
    "DND5E.ShortRestEpic": "Descanso Corto (5 minutos)",
    "DND5E.ShortRestOvernight": "Descanso Corto (Nuevo Día)",
    "DND5E.ShortRestHint": "¿Tomar un descanso corto? Con un descanso corto puedes gastar los dados de golpe restantes y recuperar recursos primarios o secundarios.",
    "DND5E.ShortRestNoHD": "No quedan dados de golpe",
    "DND5E.ShortRestResult": "{name} realiza un descanso corto gastando {dice} Dados de Golpe para recuperar {health} Puntos de Golpe.",
    "DND5E.ShortRestSelect": "Selecciona el dado a tirar",
    "DND5E.Size": "Tamaño",
    "DND5E.SizeGargantuan": "Gargantuesco",
    "DND5E.SizeHuge": "Enorme",
    "DND5E.SizeLarge": "Grande",
    "DND5E.SizeMedium": "Mediano",
    "DND5E.SizeSmall": "Pequeño",
    "DND5E.SizeTiny": "Diminuto",
    "DND5E.SkillAcr": "Acrobacias",
    "DND5E.SkillAni": "Trato con Animales",
    "DND5E.SkillArc": "Conoc. Arcano",
    "DND5E.SkillAth": "Atletismo",
    "DND5E.SkillDec": "Engaño",
    "DND5E.SkillHis": "Historia",
    "DND5E.SkillIns": "Perspicacia",
    "DND5E.SkillInv": "Investigación",
    "DND5E.SkillItm": "Intimidación",
    "DND5E.SkillMed": "Medicina",
    "DND5E.SkillNat": "Naturaleza",
    "DND5E.SkillPer": "Persuasión",
    "DND5E.SkillPrc": "Percepción",
    "DND5E.SkillPrf": "Interpretación",
    "DND5E.SkillRel": "Religión",
    "DND5E.SkillSlt": "Juego de Manos",
    "DND5E.SkillSte": "Sigilo",
    "DND5E.SkillSur": "Supervivencia",
    "DND5E.SkillPromptTitle": "Prueba de Habilidad de {skill}",
    "DND5E.Source": "Fuente",
    "DND5E.Special": "Especial",
    "DND5E.SpecialTraits": "Atributos Especiales",
    "DND5E.Speed": "Velocidad",
    "DND5E.SpeedSpecial": "Mov. Especial",
    "DND5E.SpellAbility": "Aptitud Mágica",
    "DND5E.SpellAdd": "Añadir",
    "DND5E.SpellCantrip": "Truco",
    "DND5E.SpellCastConsume": "¿Consumir espacio de conjuro?",
    "DND5E.SpellCastNoSlots": "No tienes espacios de conjuro disponibles para lanzar este conjuro.",
    "DND5E.SpellCastUpcast": "Conjurar a Nivel",
    "DND5E.SpellcasterLevel": "Nivel de Lanzador",
    "DND5E.SpellCastingHeader": "Lanzamiento de Conjuros",
    "DND5E.Spellcasting": "Aptitud Mágica",
    "DND5E.SpellComponents": "Componentes del Conjuro",
    "DND5E.SpellCreate": "Crear Conjuro",
    "DND5E.SpellDC": "CD de Conjuros",
    "DND5E.SpellDetails": "Detalles del Conjuro",
    "DND5E.SpellEffects": "Efectos del Conjuro",
    "DND5E.SpellLevel": "Nivel",
    "DND5E.SpellLevel0": "Truco",
    "DND5E.SpellLevel1": "1er Nivel",
    "DND5E.SpellLevel2": "2do Nivel",
    "DND5E.SpellLevel3": "3ro Nivel",
    "DND5E.SpellLevel4": "4to Nivel",
    "DND5E.SpellLevel5": "5to Nivel",
    "DND5E.SpellLevel6": "6to Nivel",
    "DND5E.SpellLevel7": "7mo Nivel",
    "DND5E.SpellLevel8": "8vo Nivel",
    "DND5E.SpellLevel9": "9no Nivel",
    "DND5E.SpellLevelSlot": "{level} ({n} Espacios)",
    "DND5E.SpellLevelPact": "Espacio del Pacto [Nivel {level}] ({n} Espacios)",
    "DND5E.SpellMaterials": "Materiales de conjuración",
    "DND5E.SpellName": "Nombre del conjuro",
    "DND5E.SpellNone": "Ninguno",
    "DND5E.SpellPrepAtWill": "A Voluntad",
    "DND5E.SpellPrepInnate": "Conjuro Innato",
    "DND5E.SpellPrepPrepared": "Preparado",
    "DND5E.SpellPrepAlways": "Siempre preparado",
    "DND5E.SpellPreparationMode": "Forma de Preparar el Conjuro",
    "DND5E.SpellPrepared": "Preparado",
    "DND5E.SpellProgArt": "Artificiero",
    "DND5E.SpellProgFull": "Lanzador",
    "DND5E.SpellProgHalf": "Mitad Lanzador",
    "DND5E.SpellProgOverride": "Sobrescribir Espacios",
    "DND5E.SpellProgPact": "Magia del Pacto",
    "DND5E.SpellProgThird": "Lanzador Terciario",
    "DND5E.SpellProgression": "Progreso de Conjuro",
    "DND5E.SpellSchool": "Escuela",
    "DND5E.SpellScroll": "Pergamino de Hechizo",
    "DND5E.SpellTarget": "Objetivo",
    "DND5E.SpellUnprepared": "No Preparado",
    "DND5E.SpellUsage": "Usanza",
    "DND5E.Spellbook": "L. de Conjuros",
    "DND5E.StealthDisadvantage": "DEsventaja a Sigilo",
    "DND5E.SubclassName": "Nombre de la Subclase",
    "DND5E.Supply": "Cantidad",
    "DND5E.Target": "Objetivo",
    "DND5E.TargetAlly": "Aliado",
    "DND5E.TargetCone": "Cono",
    "DND5E.TargetCreature": "Criatura",
    "DND5E.TargetCube": "Cubo",
    "DND5E.TargetCylinder": "Cilindro",
    "DND5E.TargetEnemy": "Enemigo",
    "DND5E.TargetLine": "Línea",
    "DND5E.TargetObject": "Objeto",
    "DND5E.TargetRadius": "Radio",
    "DND5E.TargetSelf": "Lanzador",
    "DND5E.TargetSpace": "Espacio",
    "DND5E.TargetSphere": "Esfera",
    "DND5E.TargetSquare": "Cuadrado",
    "DND5E.TargetWall": "Pared",
    "DND5E.Temp": "Temp",
    "DND5E.Threshold": "Umbral",
    "DND5E.TimeDay": "Día",
    "DND5E.TimeHour": "Hora",
    "DND5E.TimeInst": "Istantáneo",
    "DND5E.TimeMinute": "Minuto",
    "DND5E.TimeMonth": "Meses",
    "DND5E.TimePerm": "Permanente",
    "DND5E.TimeRound": "Ronda",
    "DND5E.TimeTurn": "Turno",
    "DND5E.TimeYear": "Año",
    "DND5E.ToolArtisans": "Herramientas de Artesano",
    "DND5E.ToolCheck": "Prueba de herramientas",
    "DND5E.ToolDisguiseKit": "Útiles para Disfrazarse",
    "DND5E.ToolForgeryKit": "Útiles para Falsificar",
    "DND5E.ToolGamingSet": "Juegos",
    "DND5E.ToolHerbalismKit": "Útiles de Herborista",
    "DND5E.ToolMusicalInstrument": "Instrumentos Musicales",
    "DND5E.ToolNavigators": "Herramientas de Navegante",
    "DND5E.ToolPoisonersKit": "Útiles de Envenenador",
    "DND5E.ToolThieves": "Herramientas de Ladrón",
    "DND5E.ToolVehicle": "Vehículos (Terrestres o Acuáticos)",
    "DND5E.TraitArmorProf": "Comp. con Armaduras",
    "DND5E.TraitSave": "Actualizar",
    "DND5E.TraitSelectorSpecial": "Especial (Separar con punto y coma)",
    "DND5E.TraitToolProf": "Comp. con Herramientas",
    "DND5E.TraitWeaponProf": "Comp. con Armas",
    "DND5E.Type": "Tipo",
    "DND5E.Unequipped": "No Equipado",
    "DND5E.Unlimited": "Ilimitado",
    "DND5E.Usage": "Uso",
    "DND5E.Use": "Carga",
    "DND5E.Uses": "Cargas",
    "DND5E.Vehicle": "Vehículo",
    "DND5E.VehicleActionStations": "Action Stations",
    "DND5E.VehicleActionThresholds": "Action Thresholds",
    "DND5E.VehicleCargo": "Carga",
    "DND5E.VehicleCargoCapacity": "Capacidad de carga",
    "DND5E.VehicleCargoCrew": "Carga y Tripulación",
    "DND5E.VehicleCreatureCapacity": "Capacidad de la criatura",
    "DND5E.VehicleCrew": "Tripulación",
    "DND5E.VehicleCrewed": "Tripulado",
    "DND5E.VehicleCrewAction": "Acción de Tripulación",
    "DND5E.VehicleEquipment": "Equipo del Vehículo",
    "DND5E.VehicleMishap": "Percance",
    "DND5E.VehiclePassengers": "Pasajeros",
    "DND5E.VehicleUncrewed": "No tripulado",
    "DND5E.Versatile": "Versátil",
    "DND5E.VersatileDamage": "Daño Versatil",
    "DND5E.VsDC": "vs CD.",
    "DND5E.WeaponImprov": "Improvisada",
    "DND5E.WeaponMartialM": "Cuerpo a C. Marcial",
    "DND5E.WeaponMartialProficiency": "Armas Marciales",
    "DND5E.WeaponMartialR": "A Distancia Marcial",
    "DND5E.WeaponNatural": "Natural",
    "DND5E.WeaponPropertiesAmm": "Munición",
    "DND5E.WeaponPropertiesFin": "Sutil",
    "DND5E.WeaponPropertiesFir": "Arma de Fuego",
    "DND5E.WeaponPropertiesFoc": "Foco",
    "DND5E.WeaponPropertiesHvy": "Pesada",
    "DND5E.WeaponPropertiesLgt": "Ligera",
    "DND5E.WeaponPropertiesLod": "Recarga",
    "DND5E.WeaponPropertiesRch": "Alcance",
    "DND5E.WeaponPropertiesRel": "Recargable",
    "DND5E.WeaponPropertiesRet": "Regresa",
    "DND5E.WeaponPropertiesSpc": "Especial",
    "DND5E.WeaponPropertiesThr": "Arrojadiza",
    "DND5E.WeaponPropertiesTwo": "A dos manos",
    "DND5E.WeaponPropertiesVer": "Versátil",
    "DND5E.WeaponSiege": "Arma de Asedio",
    "DND5E.WeaponSimpleM": "Cuerpo a C. Sencilla",
    "DND5E.WeaponSimpleProficiency": "Armas Sencillas",
    "DND5E.WeaponSimpleR": "A Distancia Sencilla",
    "DND5E.Weight": "Peso",
    "DND5E.available": "disponible",
    "DND5E.description": "Un sistema de juego completo para jugar a la quinta edición de Dungeons & Dragons en el entorno de Foundry VTT.",
    "DND5E.of": "de",
    "DND5E.spell": "conjuro",
    "SETTINGS.5eAllowPolymorphingL": "Permite a los jugadores polimorfar sus propios personajes.",
    "SETTINGS.5eAllowPolymorphingN": "Permitir Polimorfar",
    "SETTINGS.5eAutoCollapseCardL": "Contrae automáticamente la tarjeta de descripción del elemento en el registro de chat",
    "SETTINGS.5eAutoCollapseCardN": "Contraer Tarjetas de Elementos",
    "SETTINGS.5eAutoSpellTemplateL": "Cuando se lance un hechizo, de manera predeterminada creará automáticamente cualquier plantilla de medición correspondiente (requiere el rol de 'De confianza' o superior)",
    "SETTINGS.5eAutoSpellTemplateN": "Colocar Plantilla de Hechizo",
    "SETTINGS.5eCurWtL": "Las monedas que se lleven encima influyen en la carga del personaje de acuerdo con las reglas del MDJ pág. 143.",
    "SETTINGS.5eCurWtN": "Darle peso a las monedas",

    "SETTINGS.5eDiagEuclidean": "Euclidiana (7.07 pies Diagonal)",
    "SETTINGS.5eDiagL": "Seleccione la regla a usar para el movimiento diagonal en este sistema.",
    "SETTINGS.5eDiagN": "Regla para el Movimiento Diagonal",
    "SETTINGS.5eDiagPHB": "Manual del Jugador (5/5/5)",
    "SETTINGS.5eDiagDMG": "Guía del Dungeon Master (5/10/5)",
    "SETTINGS.5eInitTBL": "Agrega el puntaje de Destreza para resolver los empates de Iniciativa.",
    "SETTINGS.5eInitTBN": "Desempate de Iniciativa",
    "SETTINGS.5eNoExpL": "Elimina la barra de experiencia de las hojas de personaje.",
    "SETTINGS.5eNoExpN": "Desactivar el recuento de Experiencia",
    "SETTINGS.5eRestL": "Elige qué variante de descanso se utiliza en las partidas con este sistema.",
    "SETTINGS.5eRestN": "Variante de Descanso",
    "SETTINGS.5eRestPHB": "Manual del Jugador (DL: 8 horas, DC: 1 hora)",
    "SETTINGS.5eRestGritty": "Gritty Realism (DL: 7 días, DC: 8 horas)",
    "SETTINGS.5eRestEpic": "Epic Heroism (DL: 1 hora, DC: 1 min)"
}